{
    "N1N1_MJ_R": [
        {
            "name": "<:r:1081522963628699669> **New Jeans #1** MINJI",
            "image": "https://media.discordapp.net/attachments/1081499031949295636/1081499533600620604/nj1_mj.png?width=339&height=477",
            "footer": "You obtained the reward."
        }
    ],
    "N1N1_MJ_S": [
        {
            "name": "<:s:1081522960067727360> **New Jeans #1** MINJI ",
            "image": "https://media.discordapp.net/attachments/1081499031949295636/1081499533856481330/nj1_mj_s.png?width=339&height=477",
            "footer": "You obtained the reward."
        }
    ],
    "N1N1_MJ_A": [
        {
            "name": "<:a:1081522956234133527> **New Jeans #1** MINJI",
            "image": "https://media.discordapp.net/attachments/1081499031949295636/1081499534124912660/nj1_mj_a.png?width=339&height=477",
            "footer": "You obtained the reward."
        }
    ],
    "N1N1_MJ_B": [
        {
            "name": "<:b:1081522954279591956> **New Jeans #1** MINJI",
            "image": "https://media.discordapp.net/attachments/1081499031949295636/1081499534615650324/nj1_mj_b.png?width=339&height=477",
            "footer": "You obtained the reward."
        }
    ],
    "N1N1_MJ_C": [
        {
            "name": "<:c_:1081522950961909860> **New Jeans #1** MINJI",
            "image": "https://media.discordapp.net/attachments/1081499031949295636/1081499534363983872/nj1_mj_c.png",
            "footer": "You obtained the reward."
        }
    ]
}
